<?xml version="1.0" encoding="utf-8"?>
<WorkspaceSavedLayout xmlns:xsi="http://www.w3.org/2001/XMLSchema-instance" xmlns:xsd="http://www.w3.org/2001/XMLSchema">
  <Name>Touch</Name>
  <Root xsi:type="WorkspaceSplit">
    <LockedWidth>0</LockedWidth>
    <LockedHeight>0</LockedHeight>
    <Orientation>Vertical</Orientation>
    <Ratio>0.6454891994917408</Ratio>
    <First xsi:type="WorkspaceSplit">
      <LockedWidth>0</LockedWidth>
      <LockedHeight>0</LockedHeight>
      <Orientation>Horizontal</Orientation>
      <Ratio>0.8610963278339542</Ratio>
      <First xsi:type="WorkspaceSplit">
        <LockedWidth>0</LockedWidth>
        <LockedHeight>0</LockedHeight>
        <Orientation>Horizontal</Orientation>
        <Ratio>0.2603008502289078</Ratio>
        <First xsi:type="WorkspaceTabGroup">
          <LockedWidth>399</LockedWidth>
          <LockedHeight>0</LockedHeight>
          <Id>aa07185d-bf7d-4631-8763-849b77c95a57</Id>
          <Tabs>
            <WorkspaceTabEntry>
              <Id>cdba858f-9679-4e72-a0b8-391a49399d93</Id>
              <Editor>Console</Editor>
            </WorkspaceTabEntry>
            <WorkspaceTabEntry>
              <Id>4d659dd0-58a2-4cdf-b06b-9e0d6f01edab</Id>
              <Editor>Program</Editor>
            </WorkspaceTabEntry>
          </Tabs>
          <ActiveTabId>cdba858f-9679-4e72-a0b8-391a49399d93</ActiveTabId>
          <TabStripPlacement>Bottom</TabStripPlacement>
        </First>
        <Second xsi:type="WorkspaceLeaf">
          <LockedWidth>0</LockedWidth>
          <LockedHeight>0</LockedHeight>
          <Id>5ec809a8-7c4d-41fd-9973-88609893bcdf</Id>
          <Editor>Viewer3D</Editor>
        </Second>
      </First>
      <Second xsi:type="WorkspaceSplit">
        <LockedWidth>0</LockedWidth>
        <LockedHeight>0</LockedHeight>
        <Orientation>Vertical</Orientation>
        <Ratio>0.11003236245954692</Ratio>
        <First xsi:type="WorkspaceLeaf">
          <LockedWidth>267</LockedWidth>
          <LockedHeight>69</LockedHeight>
          <Id>56077ac2-3954-46fc-b3e4-6b1fe070bc6c</Id>
          <Editor>WorkParams</Editor>
        </First>
        <Second xsi:type="WorkspaceSplit">
          <LockedWidth>0</LockedWidth>
          <LockedHeight>0</LockedHeight>
          <Orientation>Vertical</Orientation>
          <Ratio>0.7875751503006012</Ratio>
          <First xsi:type="WorkspaceLeaf">
            <LockedWidth>0</LockedWidth>
            <LockedHeight>0</LockedHeight>
            <Id>32bb0990-5a5e-4e09-98ea-d19517787279</Id>
            <Editor>JobBar</Editor>
          </First>
          <Second xsi:type="WorkspaceLeaf">
            <LockedWidth>0</LockedWidth>
            <LockedHeight>105</LockedHeight>
            <Id>4cf8d546-ecbd-4bdc-bf5c-e7e727cb5776</Id>
            <Editor>Coolant</Editor>
          </Second>
        </Second>
      </Second>
    </First>
    <Second xsi:type="WorkspaceSplit">
      <LockedWidth>0</LockedWidth>
      <LockedHeight>0</LockedHeight>
      <Orientation>Horizontal</Orientation>
      <Ratio>0.441678520625889</Ratio>
      <First xsi:type="WorkspaceSplit">
        <LockedWidth>0</LockedWidth>
        <LockedHeight>0</LockedHeight>
        <Orientation>Horizontal</Orientation>
        <Ratio>0.5483425414364641</Ratio>
        <First xsi:type="WorkspaceLeaf">
          <LockedWidth>399</LockedWidth>
          <LockedHeight>279</LockedHeight>
          <Id>67f2247e-83b5-4d7e-acf6-ba117fcd5972</Id>
          <Editor>MdiTouch</Editor>
        </First>
        <Second xsi:type="WorkspaceLeaf">
          <LockedWidth>0</LockedWidth>
          <LockedHeight>0</LockedHeight>
          <Id>35fc0671-45ab-4093-8e6c-4ee5132929ef</Id>
          <Editor>Dro</Editor>
        </Second>
      </First>
      <Second xsi:type="WorkspaceSplit">
        <LockedWidth>0</LockedWidth>
        <LockedHeight>0</LockedHeight>
        <Orientation>Horizontal</Orientation>
        <Ratio>0.7309184993531694</Ratio>
        <First xsi:type="WorkspaceSplit">
          <LockedWidth>0</LockedWidth>
          <LockedHeight>0</LockedHeight>
          <Orientation>Horizontal</Orientation>
          <Ratio>0.6123893805309735</Ratio>
          <First xsi:type="WorkspaceLeaf">
            <LockedWidth>0</LockedWidth>
            <LockedHeight>0</LockedHeight>
            <Id>b0778e67-8049-465e-ac1a-ec583cd3f66c</Id>
            <Editor>Jog</Editor>
          </First>
          <Second xsi:type="WorkspaceLeaf">
            <LockedWidth>224</LockedWidth>
            <LockedHeight>0</LockedHeight>
            <Id>219f03ef-99f6-49da-af60-d79e091d8e8d</Id>
            <Editor>FeedTouch</Editor>
          </Second>
        </First>
        <Second xsi:type="WorkspaceLeaf">
          <LockedWidth>213</LockedWidth>
          <LockedHeight>0</LockedHeight>
          <Id>154ffb6c-bcdc-4edc-b4ed-aca2cdc0f6d6</Id>
          <Editor>SpindleTouch</Editor>
        </Second>
      </Second>
    </Second>
  </Root>
  <QuickAccessSidebar>
    <Enabled>false</Enabled>
    <ShowLeft>false</ShowLeft>
    <ShowRight>false</ShowRight>
    <Dock>Right</Dock>
    <LegacySidesMigrated>true</LegacySidesMigrated>
    <Tabs>
      <QuickAccessTabEntry>
        <Id>f8347fad-7c04-41d9-a6f9-f12ecec9dabb</Id>
        <EditorId>Jog</EditorId>
        <PopupWidth>453</PopupWidth>
        <PopupHeight>292</PopupHeight>
      </QuickAccessTabEntry>
      <QuickAccessTabEntry>
        <Id>4e05ea01-5c11-4ca6-8b90-80477defd97b</Id>
        <EditorId>Macros</EditorId>
        <PopupWidth>300</PopupWidth>
        <PopupHeight>174</PopupHeight>
      </QuickAccessTabEntry>
      <QuickAccessTabEntry>
        <Id>cb009626-c613-40f4-8412-378882717d19</Id>
        <EditorId>Goto</EditorId>
        <PopupWidth>250</PopupWidth>
        <PopupHeight>178</PopupHeight>
      </QuickAccessTabEntry>
    </Tabs>
  </QuickAccessSidebar>
</WorkspaceSavedLayout>